CMakeLists.txt
README.md
config.h.cmake
dune.module
projectname.pc.in
pyproject.toml
setup.py
DockerImages/DockerFile
cmake/modules/CMakeLists.txt
cmake/modules/ProjectnameMacros.cmake
projectname/CMakeLists.txt
projectname/foo.cpp
projectname/foo.hh
projectname/python/CMakeLists.txt
projectname/python/projectname/CMakeLists.txt
projectname/python/projectname/enums.hh
projectname/python/test/CMakeLists.txt
projectname/python/test/test1.py
projectname/python/test/test2.py
python/CMakeLists.txt
python/setup.py.in
python/projectname/CMakeLists.txt
python/projectname/__init__.py
python/projectname/_projectname.cc
python/projectnameTest.egg-info/PKG-INFO
python/projectnameTest.egg-info/SOURCES.txt
python/projectnameTest.egg-info/dependency_links.txt
python/projectnameTest.egg-info/requires.txt
python/projectnameTest.egg-info/top_level.txt