Metadata-Version: 2.1
Name: projectnameTest
Version: 0.1.dev20230214
Home-page: 
Author: mueller@ibb.uni-stuttgart.de
Author-email: mueller@ibb.uni-stuttgart.de
Classifier: Programming Language :: C++
Classifier: Programming Language :: Python :: 3
Classifier: License :: OSI Approved :: GNU General Public License (GPL)
Requires-Python: >=3.4
